constants/__init__.py
constants/models_exporter.py
constants/serializers_exporter.py
django_ts_exporter/__init__.py
django_ts_exporter/exporter.py
django_ts_exporter/models_exporter.py
django_ts_exporter/serializers_exporter.py
django_ts_exporter/utils.py
tests/__init__.py
tests/models.py
tests/serializers.py
tests/test_models_exporter.py
tests/test_serializers_exporter.py
django_ts_exporter-0.4.0.dist-info/LICENSE
django_ts_exporter-0.4.0.dist-info/METADATA
django_ts_exporter-0.4.0.dist-info/WHEEL
django_ts_exporter-0.4.0.dist-info/entry_points.txt
django_ts_exporter-0.4.0.dist-info/top_level.txt
django_ts_exporter-0.4.0.dist-info/RECORD
