Metadata-Version: 2.1
Name: django-ts-exporter
Version: 0.4.0
Summary: Export Django models and serializers to TypeScript interfaces
Home-page: https://github.com/gmartinu/django-ts-exporter
Author: Gabriel Martinusso
Author-email: gabrielbramos@outlook.com
License: UNKNOWN
Platform: UNKNOWN
Classifier: Programming Language :: Python :: 3
Classifier: Framework :: Django
Classifier: License :: OSI Approved :: MIT License
Classifier: Operating System :: OS Independent
Requires-Python: >=3.6
Requires-Dist: Django >=3.0
Requires-Dist: djangorestframework >=3.11
